Metadata-Version: 1.1
Name: magpie
Version: 0.0.7
Summary: magpie: [ma]rkdown, [g]it, [pie]thon
Home-page: https://github.com/charlesthomas/magpie
Author: Charles Thomas
Author-email: ch@rlesthom.as
License: The MIT License (MIT)
